xgcondb/__about__.py
xgcondb/__init__.py
xgcondb-800424.63.21.dist-info/METADATA
xgcondb-800424.63.21.dist-info/WHEEL
xgcondb-800424.63.21.dist-info/licenses/LICENSE
xgcondb-800424.63.21.dist-info/RECORD
