Metadata-Version: 2.3
Name: xgcondb
Version: 800424.63.21
Summary: XuGu Database Python Driver
Project-URL: Documentation, https://github.com/Jedore/XuGu-Python-Driver#readme
Project-URL: Issues, https://github.com/Jedore/XuGu-Python-Driver/issues
Project-URL: Source, https://github.com/Jedore/XuGu-Python-Driver
Author-email: Jedore <jedorefight@gmail.com>
License: Apache-2.0
Keywords: DB,XuGu,xgcondb
Classifier: License :: OSI Approved :: Apache Software License
Classifier: Operating System :: Microsoft :: Windows
Classifier: Operating System :: POSIX :: Linux
Classifier: Programming Language :: Python
Classifier: Programming Language :: Python :: 3.6
Classifier: Programming Language :: Python :: 3.7
Classifier: Programming Language :: Python :: 3.8
Classifier: Programming Language :: Python :: 3.9
Classifier: Programming Language :: Python :: 3.10
Classifier: Programming Language :: Python :: 3.11
Classifier: Programming Language :: Python :: Implementation :: CPython
Requires-Python: <3.12,>=3.6
